MANIFEST.in
base.py
setup.py
StringConditions.egg-info/PKG-INFO
StringConditions.egg-info/SOURCES.txt
StringConditions.egg-info/dependency_links.txt
StringConditions.egg-info/top_level.txt