Metadata-Version: 1.0
Name: StringConditions
Version: 0.1
Summary: A small python package which evaluates string based conditions
Home-page: https://github.com/ciokan/string_condition
Author: Mihalcea Romeo
Author-email: romeo.mihalcea@gmail.com
License: MIT
Platform: UNKNOWN
